_pyfxr.cp36-win_amd64.pyd
pyfxr.py
pyfxr_gui.py
pyfxr-0.3.0.dist-info/LICENSE
pyfxr-0.3.0.dist-info/METADATA
pyfxr-0.3.0.dist-info/WHEEL
pyfxr-0.3.0.dist-info/entry_points.txt
pyfxr-0.3.0.dist-info/top_level.txt
pyfxr-0.3.0.dist-info/RECORD
