Metadata-Version: 2.1
Name: pyfxr
Version: 0.3.0
Summary: SFXR clone using Pygame and Cython
Home-page: https://github.com/lordmauve/pyfxr
Author: Daniel Pope
Author-email: mauve@mauveweb.co.uk
License: UNKNOWN
Platform: UNKNOWN
Classifier: Development Status :: 5 - Production/Stable
Classifier: License :: OSI Approved :: BSD License
Classifier: Programming Language :: Python :: 3
Provides-Extra: gui
